blast_ct/__init__.py
blast_ct/console_tool.py
blast_ct/inference.py
blast_ct/read_config.py
blast_ct/train.py
blast_ct/data/config.json
blast_ct/localisation/__init__.py
blast_ct/localisation/localise_lesions.py
blast_ct/localisation/register_to_template.py
blast_ct/models/__init__.py
blast_ct/models/base.py
blast_ct/models/deepmedic.py
blast_ct/nifti/__init__.py
blast_ct/nifti/augmention.py
blast_ct/nifti/datasets.py
blast_ct/nifti/patch_samplers.py
blast_ct/nifti/rescale.py
blast_ct/nifti/savers.py
blast_ct/nifti/transformation.py
blast_ct/trainer/__init__.py
blast_ct/trainer/hooks.py
blast_ct/trainer/inference.py
blast_ct/trainer/logger.py
blast_ct/trainer/losses.py
blast_ct/trainer/metrics.py
blast_ct/trainer/model_trainer.py
blast_ct/utils/config_loader.py
blast_ct/utils/model_loader.py
blast_ct-5.0.5.dist-info/licenses/LICENSE.txt
blast_ct-5.0.5.dist-info/METADATA
blast_ct-5.0.5.dist-info/WHEEL
blast_ct-5.0.5.dist-info/entry_points.txt
blast_ct-5.0.5.dist-info/top_level.txt
blast_ct-5.0.5.dist-info/RECORD
