Metadata-Version: 2.4
Name: blast_ct
Version: 5.0.5
Summary: Automatic segmentation of Traumatic Brain Injury (TBI) in Head CT
Author-email: Sakshi Rathi <rathi036@umn.edu>, Miguel Monteiro <miguel.monteiro@imperial.ac.uk>
Maintainer-email: Sakshi Rathi <rathi036@umn.edu>
License: MIT
Project-URL: Repository, https://github.com/biomedia-mira/blast_ct
Keywords: CT,traumatic brain injury,segmentation,medical imaging
Requires-Python: >=3.6
License-File: LICENSE.txt
Requires-Dist: scipy
Requires-Dist: numpy
Requires-Dist: pandas
Requires-Dist: torch
Requires-Dist: tensorboard
Requires-Dist: SimpleITK==1.2.4; python_version < "3.9"
Requires-Dist: SimpleITK<2.4.0,>=2.0.2; python_version >= "3.9"
Dynamic: license-file
